gribberish-0.27.1.dist-info/METADATA
gribberish-0.27.1.dist-info/WHEEL
gribberish-0.27.1.dist-info/entry_points.txt
gribberish.libs/libgcc_s-262c4f60.so.1
gribberish/__init__.py
gribberish/_gribberish_python.cpython-314-arm-linux-musleabihf.so
gribberish/gribberish_backend.py
gribberish/kerchunk/__init__.py
gribberish/kerchunk/codec.py
gribberish/kerchunk/mapper.py
gribberish/zarr/__init__.py
gribberish/zarr/codec.py
gribberish-0.27.1.dist-info/RECORD
