Metadata-Version: 2.4
Name: gribberish
Version: 0.27.1
Classifier: Programming Language :: Rust
Classifier: Programming Language :: Python :: Implementation :: CPython
Classifier: Programming Language :: Python :: Implementation :: PyPy
Requires-Dist: numpy>=2
Requires-Dist: xarray ; extra == 'xarray'
Requires-Dist: fsspec ; extra == 'xarray'
Requires-Dist: kerchunk ; extra == 'kerchunk'
Requires-Dist: zarr ; extra == 'kerchunk'
Requires-Dist: numcodecs ; extra == 'kerchunk'
Requires-Dist: fsspec ; extra == 'kerchunk'
Requires-Dist: zarr>3.0.0 ; extra == 'zarr'
Requires-Dist: matplotlib ; extra == 'dev'
Requires-Dist: cf-xarray ; extra == 'dev'
Requires-Dist: zarr ; extra == 'dev'
Requires-Dist: numcodecs ; extra == 'dev'
Requires-Dist: fsspec ; extra == 'dev'
Requires-Dist: ujson ; extra == 'dev'
Requires-Dist: dask[complete] ; extra == 'dev'
Requires-Dist: ipywidgets ; extra == 'dev'
Requires-Dist: scipy ; extra == 'dev'
Requires-Dist: gcsfs ; extra == 'dev'
Requires-Dist: s3fs ; extra == 'dev'
Requires-Dist: cfgrib ; extra == 'dev'
Requires-Dist: pyproj ; extra == 'dev'
Requires-Dist: pytest ; extra == 'dev'
Requires-Dist: pytest-asyncio ; extra == 'dev'
Provides-Extra: xarray
Provides-Extra: kerchunk
Provides-Extra: zarr
Provides-Extra: dev
Requires-Python: >=3.11
